{
    "2026-01-12": [
        {
            "start_time": "9:00",
            "end_time": "10:00",
            "text": "lol"
        },
        {
            "start_time": "10:00",
            "end_time": "11:00",
            "text": "sdffsd"
        },
        {
            "start_time": "11:00",
            "end_time": "13:00",
            "text": "test migrate"
        }
    ],
    "2026-02-25": [
        {
            "start_time": "8:00",
            "end_time": "10:00",
            "text": "test"
        },
        {
            "start_time": "10:00",
            "end_time": "11:00",
            "text": "run"
        },
        {
            "start_time": "11:00",
            "end_time": "12:00",
            "text": "lol"
        },
        {
            "start_time": "12:00",
            "end_time": "13:00",
            "text": "qwdqwd"
        },
        {
            "start_time": "13:00",
            "end_time": "14:00",
            "text": "sdffdssdf"
        },
        {
            "start_time": "14:00",
            "end_time": "15:00",
            "text": "sdsadads"
        }
    ],
    "2026-02-26": [],
    "2026-02-27": [
        {
            "start_time": "8:00",
            "end_time": "10:00",
            "text": "test"
        },
        {
            "start_time": "11:00",
            "end_time": "12:00",
            "text": "test2"
        },
        {
            "start_time": "13:00",
            "end_time": "14:00",
            "text": "test change files"
        }
    ],
    "2026-02-28": [
        {
            "start_time": "8:00",
            "end_time": "10:00",
            "text": "test"
        },
        {
            "start_time": "11:00",
            "end_time": "12:00",
            "text": "dsfdsf"
        },
        {
            "start_time": "13:00",
            "end_time": "14:00",
            "text": "sdf"
        }
    ],
    "2026-03-01": []
}